<?xml version="1.0" encoding="utf-8"?>
  <?xml-stylesheet type="text/xsl" href="rfc2629.xslt" ?>
  <!-- generated by https://github.com/cabo/kramdown-rfc version 1.7.5 (Ruby 3.3.0) -->


<!DOCTYPE rfc  [
  <!ENTITY nbsp    "&#160;">
  <!ENTITY zwsp   "&#8203;">
  <!ENTITY nbhy   "&#8209;">
  <!ENTITY wj     "&#8288;">

]>

<?rfc comments="yes"?>

<rfc ipr="trust200902" docName="draft-awayf-00" category="info" tocInclude="true" sortRefs="true" symRefs="true">
  <front>
    <title abbrev="A-WAYF">Automated Where Are You From in Multilateral Federations</title>

    <author initials="E." surname="Kupris" fullname="Erwin Kupris">
      <organization></organization>
      <address>
        <email>erwin.kupris@hm.edu</email>
      </address>
    </author>
    <author initials="T." surname="Hilbig" fullname="Tobias Hilbig">
      <organization></organization>
      <address>
        <email>tobias.hilbig@hm.edu</email>
      </address>
    </author>
    <author initials="D. P." surname="Sugar" fullname="David Pierre Sugar">
      <organization></organization>
      <address>
        <email>sugar@hm.edu</email>
      </address>
    </author>
    <author initials="T." surname="Schreck" fullname="Thomas Schreck">
      <organization></organization>
      <address>
        <email>thomas.schreck@hm.edu</email>
      </address>
    </author>

    <date year="2024" month="February" day="10"/>

    
    
    

    <abstract>


<?line 107?>

<t>This document introduces a extension to the CTAP2 protocol that
allows the storage of enterprise federation credentials and the
enumeration of their corresponding identity providers.</t>



    </abstract>



  </front>

  <middle>


<?line 113?>

<section anchor="introduction"><name>Introduction</name>

<section anchor="requirements"><name>Requirements</name>

</section>
<section anchor="terminology"><name>Terminology</name>

<t>The key words "MUST", "MUST NOT", "REQUIRED", "SHALL", "SHALL NOT", "SHOULD", 
"SHOULD NOT", "RECOMMENDED", "NOT RECOMMENDED", "MAY", and "OPTIONAL" in this document 
are to be interpreted as described in BCP 14 <xref target="RFC2119"/> <xref target="RFC8174"/> when, and only when, they appear in all 
capitals, as shown here.</t>

<t>The term "byte" is used in its now-customary sense as a synonym for "octet".</t>

<t>This document makes use of the following terminology:</t>

<dl>
  <dt>authenticator:</dt>
  <dd>
    <t>An Authenticator is software that implements the CTAP protocol and is able to create new credentials and make assertions on request. It interacts with a Client through a communication channel like CTAPHID, which builds on top of USB HID.</t>
  </dd>
  <dt>client:</dt>
  <dd>
    <t>A Client is software that implements the client-side part of the CTAP protocol. It acts as a middleman between a Authenticator and a Relying Party.</t>
  </dd>
  <dt>RP:</dt>
  <dd>
    <t>A Relying Party (RP) is a web-service one can authenticate to using the FIDO authentication protocol. It communicates indirectly with an Authenticator through the Client and is responsible for initiating a authentication ceremony.</t>
  </dd>
  <dt>confidentiality:</dt>
  <dd>
    <t>Confidentiality relates to the state of data in which only authorized entities can comprehend its content. Typically, this is ensured through encryption, where only the possessor of the correct secret key can decrypt the data and gain access to its actual content.</t>
  </dd>
  <dt>integrity:</dt>
  <dd>
    <t>Integrity pertains to the condition of data wherein no unauthorized alterations have occurred. Unintended modifications may occur inadvertently, such as a bit-flip resulting from hardware failure, or intentionally by an adversary with access to the data. The concept of "protecting data integrity" encompasses the ability to identify undesired changes before they can impact a system in any conceivable manner.</t>
  </dd>
  <dt>authenticity:</dt>
  <dd>
    <t>Authenticity denotes the ability to confirm that specific data has been generated by a particular source. This validation can be implemented through cryptographic concepts such as digital signatures or Message Authentication Codes. Frequently, a single cryptographic primitive can be employed to ensure both integrity and authenticity.</t>
  </dd>
  <dt>identity provider:</dt>
  <dd>
    <t>A identity provider TODO</t>
  </dd>
</dl>

</section>
</section>
<section anchor="ctap2-extension"><name>CTAP2 Extension</name>

<t>The following section introduces a extension for <xref target="CTAP"/> that adds a new field (idpId) which marks a credential as belonging to an identity provider.</t>

<section anchor="enterprise-federation-enterprisefed"><name>Enterprise Federation (enterpriseFed)</name>

<section anchor="feature-detection"><name>Feature detection</name>

<dl>
  <dt>Extension identifier:</dt>
  <dd>
    <t>federationId</t>
  </dd>
</dl>

<t>This registration extension allows relying parties to specify an federation entity when creating a credential.</t>

</section>
<section anchor="client-extension"><name>Client extension</name>

<section anchor="client-extension-input"><name>Client extension input</name>

<t>create(): A single USVString specifying the federation entity.</t>

<figure title="Extension client input" anchor="figops"><artwork><![CDATA[
partial dictionary AuthenticationExtensionsClientInputs {
  USVString idpId;
};
]]></artwork></figure>

</section>
<section anchor="client-extension-processing"><name>Client extension processing</name>

<t>If this extension is present in an authenticatorMakeCredential request:</t>

<t><list style="numbers">
  <t>Verify that the fedEntity string value is valid:
  <list style="symbols">
      <t>TODO: verification criteria depend on the format (do we want UUID v4/v7 ?)</t>
    </list></t>
</list></t>

<t>NOTE: For non-discoverable credentials, the fedEntity has no effect on the authenticators behaviour.</t>

</section>
<section anchor="client-extension-output"><name>Client extension output</name>

<t>None. The authenticator returns the result in the authenticator extension output.</t>

</section>
</section>
<section anchor="authenticator-extension"><name>Authenticator extension</name>

<section anchor="authenticator-extension-input"><name>Authenticator extension input</name>

<t>The platform sends the authenticatorMakeCredential request with the following CBOR map entry in the "extensions" field to the authenticator:</t>

<t><list style="symbols">
  <t>"idpId":&lt;fedEntity Value&gt;</t>
</list></t>

<t>NOTE: The extension SHOULD be ignored for non-discoverable credentials.</t>

<figure title="Sample CTAP2 authenticatorMakeCredential Request (CBOR)" anchor="figops2"><artwork><![CDATA[
{
    ...
    6: {"idpId": "https://shi-idp2.rz.fh-muenchen.de/idp/shibboleth"},
    ...
}
]]></artwork></figure>

</section>
<section anchor="authenticator-extension-processing"><name>Authenticator extension processing</name>

<t>The authenticator checks whether the authenticatorMakeCredential's options.rk option is present and true. If so, the authenticator stores the given information with the created credential. If not, the authenticator SHOULD ignore the extension.</t>

</section>
<section anchor="authenticator-extension-output"><name>Authenticator extension output</name>

<t>If the authenticator has set the extensions value for the credential:</t>

<t><list style="symbols">
  <t>"idpId":&lt;enterpriseFed Value&gt;</t>
</list></t>

<t>Else:</t>

<t><list style="symbols">
  <t>None.</t>
</list></t>

</section>
</section>
</section>
</section>
<section anchor="ctap2-command"><name>CTAP2 Command</name>

<section anchor="prototype-authenticatorfederationmanagement-0x42"><name>Prototype authenticatorFederationManagement (0x42)</name>

<t>This command is used by the platform to manage federated credentials on the authenticator.</t>

<t>It takes the following input parameters:</t>

<texttable>
      <ttcol align='center'>Parameter name</ttcol>
      <ttcol align='center'>Data type</ttcol>
      <ttcol align='center'>Required?</ttcol>
      <ttcol align='left'>Definition</ttcol>
      <c>subCommand (0x01)</c>
      <c>Unsigned Integer</c>
      <c>Required</c>
      <c>subCommand currently being requested</c>
      <c>pinUvAuthProtocol (0x02)</c>
      <c>Unsigned Integer</c>
      <c>Optional</c>
      <c>PIN/UV protocol version selected by platform.</c>
      <c>pinUvAuthParam (0x03)</c>
      <c>Byte String</c>
      <c>Optional</c>
      <c>Result of calling authenticate(pinUvAuthToken, Prototype authenticatorFederationManagement (0x42))</c>
</texttable>

<t>The list of sub commands for credential management is:</t>

<texttable>
      <ttcol align='center'>subCommand Name</ttcol>
      <ttcol align='center'>subCommand Number</ttcol>
      <c>enumerateIdPBegin</c>
      <c>0x01</c>
      <c>enumerateIdPsGetNextIdP</c>
      <c>0x02</c>
</texttable>

<t>On success, authenticator returns the following structure in its response:</t>

<texttable>
      <ttcol align='center'>Parameter name</ttcol>
      <ttcol align='center'>Data type</ttcol>
      <ttcol align='center'>Definition</ttcol>
      <c>idpId (0x01)</c>
      <c>Text String</c>
      <c>IdP entity id</c>
      <c>totalIdps (0x02)</c>
      <c>Unsigned Integer</c>
      <c>total number of IdPs present on the authenticator</c>
</texttable>

<section anchor="enumerateidpbegin-0x01"><name>enumerateIdPBegin (0x01)</name>

<t>Following operations are preformed to enumerate the identity providers present on the authenticator:</t>

<t><list style="symbols">
  <t>The platform gets a pinUvAuthToken from the authenticator with the cm (0x04) permission.</t>
  <t>The Platform sends a authenticatorEnumerateIdP command with the following parameters:
  <list style="symbols">
      <t>pinUvAuthProtocol (0x02): as selected when getting the shared secret.</t>
      <t>pinUvAuthParam (0x03): authenticate(pinUvAuthToken, authenticatorFederationManagement (0x42)).</t>
    </list></t>
  <t>Authenticator on receiving such request performs following procedures:
  <list style="numbers">
      <t>If one of the expected arguments is missing from the input map, return CTAP2_ERR_MISSING_PARAMETER.</t>
      <t>If pinUvAuthProtocol is not supported, return CTAP1_ERR_INVALID_PARAMETER.</t>
      <t>Authenticator calls verify(pinUvAuthToken, authenticatorFederationManagement (0x42), pinUvAuthParam).</t>
      <t>If pinUvAuthParam verification fails, authenticator returns CTAP2_ERR_PIN_AUTH_INVALID error.</t>
      <t>The authenticator verifies that the pinUvAuthToken has the cm permission. If not, return CTAP2_ERR_PIN_AUTH_INVALID.</t>
      <t>If no discoverable credentials exist on this authenticator, return CTAP2_ERR_NO_IDPS.</t>
      <t>Locate all credentials that are eligible for retrieval under the specified criteria:
      <list style="numbers">
          <t>Locate all discoverable credentials that are created by this authenticator that have the fedEntity property.</t>
          <t>Create an applicable credentials list populated with the located credentials.</t>
          <t>Iterate through the applicable credentials list, and if credential protection for a credential is marked as userVerificationRequired or userVerificationOptionalWithCredentialIDList, and the pinUvAuthParam is missing from the input map, remove that credential from the applicable credentials list.</t>
          <t>If the applicable credentials list is empty, return CTAP2_ERR_NO_IDPS.</t>
          <t>Let numberOfIdPs be the number of applicable credentials found.</t>
        </list></t>
      <t>Authenticator returns an authenticatorFederationManagement response with following parameters:
      <list style="symbols">
          <t>idpId (0x01): Text String, the content of fedEntity.</t>
          <t>totalIdps (0x02): Total number of IdPs present on the authenticator. This can vary depending on if a pinUvAuthParam was sent with the request.</t>
        </list></t>
    </list></t>
  <t>Platform on receiving more than 1 totalIdps, performs following procedure for (totalIdps - 1 ) number of times:
  <list style="symbols">
      <t>Platform sends authenticatorFederationManagement command with following parameters:
      <list style="symbols">
          <t>subCommand (0x01): enumerateIdPsGetNextIdP (0x02).</t>
        </list></t>
      <t>Authenticator on receiving such enumerateIdPsGetNextIdP subCommand returns authenticatorFederationManagement response with following parameters:
      <list style="symbols">
          <t>idpId (0x01): Text String, the content of fedEntity.</t>
        </list></t>
    </list></t>
</list></t>

</section>
</section>
</section>
<section anchor="ctap2-status-codes"><name>CTAP2 Status codes</name>

<t>This extension also introduces a new status code that has to be added
to the table of available status codes.</t>

<texttable>
      <ttcol align='center'>Code</ttcol>
      <ttcol align='center'>Name</ttcol>
      <ttcol align='center'>Description</ttcol>
      <c>0xE1</c>
      <c>CTAP2_ERR_NO_IDPS</c>
      <c>There are no available IdPs. This can have two reasons: 1) there are really no discoverable credentials marked as federation key 2) there are federation credentials that have a credential protection policy greater than optional but the client didn't provide a pinUvAuthToken.</c>
</texttable>

</section>
<section anchor="security-considerations"><name>Security Considerations</name>

</section>


  </middle>

  <back>


    <references title='Normative References' anchor="sec-normative-references">

<reference anchor="RFC2119" target="https://www.rfc-editor.org/info/rfc2119">
  <front>
    <title>Key words for use in RFCs to Indicate Requirement Levels</title>
    <author initials="S." surname="Bradner" fullname="Scott Bradner">
      <organization>Harvard University</organization>
    </author>
    <date year="1997" month="March"/>
  </front>
</reference>
<reference anchor="RFC8174" target="https://www.rfc-editor.org/info/rfc8174">
  <front>
    <title>Ambiguity of Uppercase vs Lowercase in RFC 2119 Key Words</title>
    <author initials="B." surname="Leiba" fullname="Barry Leiba">
      <organization>Huawei Technologies</organization>
    </author>
    <date year="2017" month="May"/>
  </front>
</reference>
<reference anchor="CTAP" target="https://fidoalliance.org/specs/fido-v2.2-rd-20230321/fido-client-to-authenticator-protocol-v2.2-rd-20230321.html#getPinUvAuthTokenUsingPinWithPermissions">
  <front>
    <title>Client to Authenticator Protocol (CTAP)</title>
    <author initials="J." surname="Bradley" fullname="John Bradley">
      <organization>Yubico</organization>
    </author>
    <author initials="J." surname="Hodges" fullname="Jeff Hodges">
      <organization>Google</organization>
    </author>
    <author initials="M. B." surname="Jones" fullname="Michael B. Jones">
      <organization>Microsoft</organization>
    </author>
    <author initials="A." surname="Kumar" fullname="Akshay Kumar">
      <organization>Microsoft</organization>
    </author>
    <author initials="R." surname="Lindemann" fullname="Rolf Lindemann">
      <organization>Nok Nok Labs</organization>
    </author>
    <author initials="J." surname="Verrept" fullname="Johan Verrept">
      <organization>OneSpan</organization>
    </author>
    <date year="2023" month="March" day="21"/>
  </front>
</reference>


    </references>

    <references title='Informative References' anchor="sec-informative-references">

<reference anchor="WebAuthn" target="https://www.w3.org/TR/webauthn/">
  <front>
    <title>Web Authentication An API for accessing Public Key Credentials Level 2</title>
    <author initials="J." surname="Hodges" fullname="Jeff Hodges">
      <organization>Google</organization>
    </author>
    <author initials="J. C." surname="Jones" fullname="J. C. Jones">
      <organization>Mozilla</organization>
    </author>
    <author initials="M. B." surname="Jones" fullname="Michael B. Jones">
      <organization>Microsoft</organization>
    </author>
    <author initials="A." surname="Kumar" fullname="Akshay Kumar">
      <organization>Microsoft</organization>
    </author>
    <author initials="E." surname="Lundberg" fullname="Emil Lundberg">
      <organization>Yubico</organization>
    </author>
    <date year="2021" month="April" day="08"/>
  </front>
</reference>


    </references>



  </back>

<!-- ##markdown-source:
H4sIAAAAAAAAA+1a23LbSJJ9x1dUyA8jTYiQRHu2uzm7OytLcps9uq0udnTs
bDiKQJGsEIjCogpis23Pt8/JrMKNFCWPHzb2YRV2iAQKmVmZJzNPFjQYDKLE
pDqfjUTlpoMfo8hpl6mROK6cWUinUvFxrkoljvH/V1OJd6VZCJ2LiypzOsOC
UmbinUrx22mT20hOJqV6hIDBx+Nf30WpSXK5gMC0lFM3kEu5mg4OD6MEj85M
uRpB2NREuihHwpWVdcPDw58Oh1FknczTTzIzOR5eKRsVeiT+y5lkX1hTulJN
LT6tFv5DYhYLlTv731EkKzc35SgSYoD/AvLtSJzF4q9VUWrLl7xFZ+USG+lc
Vgups5FQdD1+4Ov/MV/EKq36wu5i8V5nEz3rCLszEy1t93qQ5vhGPOcbT4o7
jcV1LG6rmSw7Ak/lo07FtVYlPN/eDFItXdhm3G0yL1Xy0LVujmDa3o3aPL4T
W3+nlhjlpkT09aMa8eKbdyfDo6Of/Bf6cbKcKTcSc+cKOzo4WC6XcTlNBirV
zpSxKWcHFNcDXKMHRfugh9df1UosTZlaMTWlqKwiTEGLhb/EOE814UPcqP+p
dKkosuJcParMNnLaKLc/g963xiO3sXhbyjRX5cZ9753bxDi3dQ32MhLvZfko
y1Tc5/BJabVbNetSWDoSRz/99MPg8HXtrR+PfnjzXd6iB9eddbwAdCroFGYq
7otClYmExx6tODfL8MW7T7Czybkfybnf4623MVytJ3KLr97KslxtWeE9Vcml
0uJOJfPcZGamlV1z1fDwCK76E189uTu+3u6nqU6NzDIt80Sxl2yhEsuXB4/D
eDgo08HwcPj68PXwyF9NMg2wDJwZ0JbxkYBkykFRGpQOk208Fs/dInsFrdc6
v39E1ZvfmQeV31vURFz6qN38WpULbS1Xt7XInLA6wuxxV524DurELm1w73vi
8ItHbaZWWyLxi5nnW5dwKH6tJjox36jsvUlnnVCt6VLT6bYVrOpnY2aZ+hZV
FzFB7BeU9W3KLnQylyrbvow1YlVprJm6b1F6TOV/IbcVgOMHO5erLUv+eW03
SCGdp6iweb5F443Jps8sYp2X5oH/n8uJ/cYgfqBuUbjtiJH51jWs8ypXt4XM
NzJ2+BrFbTA8iiIqVL3e8FFNCPz58+Vu+ZoT+O7mYKkmlAb5wXoyQVA3jZBv
4hj/rsfcI2SSKEtZKa6rSaYTrnInJZgHlsvM+gYhht+Za/9b8Ieqk+fh/9wK
j0Xzu84y+f/JVjO78ypPJ6qcbVF4ttDZ9jVPVcoG9UeDwzeDQ7DiwWAgkIau
lImLoru5tgLMtmJmonNXmrQCPIUU6jencuoV1BSAZe5wQ1H3H1ySLkJPM0vL
ty3ahZwp6uyQpUoinUpMG0Itkg7EwYjpoUjl0Bzu40Fc0iUoMPLaFiYnOi80
PwTKAM0gkuAssd/FQqfoGFH0CjTL201i8P1Vl25ZvnBHnY+7+Io2rcRDQ9t2
Lu5v73b2/W9xecWfb87+8358c3ZKn2/fH5+fNx/qFbfvr+7P6X4UPraPnlxd
XJxdnvqncVWsXbo4/hW/yAU7V9d346vL4/Mdoj2uF4xIgi7D9ROiROxPRUMM
yG+qbFLqCb7gobcn1+Lojfj8OTDbr1/9Z6Jf+LxEEfK6TJ6twle4eSUk6Jcs
SQSCKDDGFNohNPukwc7NMhc0LsXeXdC/EDuTlVOw1BLNZeXaWZGb5SDBuAP2
DT5lgRlFIiRGmtzkqwXXvB2TOOV2YrEOuYV8UCwvhB+rCVIUeNfGbOSHoYaW
jEQ04pLa4yqQS7m2ZMcBnUIvisyDoAFwi1/yCZ6Qk4zdDHQSUc/VcgOoZCO2
ZFXJgyE8KUoATFkXi7Hz0UE2WbEEx8LGay41L001ows001V53QpQpvIchSrT
D96m9+PTfUQG9UtMKp2lrMGZgkny7VuB+wiDJ4R+57WKl3YcSKRF2ohClq52
cs8TvAm2n8Pm0wrNHMhzS6WAjzU/k08kcixbcROD3BXsu7kOtvVuiN2b6z32
s0C7HMCHjzpBsHMYBxWdqHIUKu6LZOK78elV9zZ5rmdx61QACPwD+Z44gjgH
YR0bdTB49955AQC+1FhNOCCo6lwj9I7skOsGJMiIBUBN4TD5VAeYoDrx3k/6
1yA6Y+tCAbWOdokQoCpLSh8fc05M3+P178grLncYNthB2CUSHzaknGzQiqoM
3N2tChiVZat9XzbwD5lXAbnNVlWelKuC7CZ00dEHayJLCgM0W4vdBkBwyU0c
0hfgd1wdSXuqWAQvYaPJZzNJNYNJDO2MzAJ6Kpk11hG3cmpW1n4Z198EJj6H
xxuXJFTk6+rPGthSKMgBhrzjFZm5+mRGzOUjNpMkFYxOYxplSW+KVQuT6mmI
lkXirvwyOFumGHfJOnKZreB3RvtEu8E00wXBgA6CEPUpHQzNMSNzWk2lzuDW
fcHQIAEQTY4XkxXBjOVaKn0eeI1fap8hVn6jCbgqbXOHYAxnk66AhOCeHYoZ
Ak61xiewnGhGEvmZgTVdwS1oAJoiTZUETA6JCuAqX9YpbKgCiAiXYOsUn3LJ
fOVt0I9c8YisqzLu1NU6WMedCwBAbtymLQx+dASuOTTKktP9ZuaS7EHVmKmc
AgYzyVFcfnRSZWg51lQlxmDBneARqZKG7OKa09awDpYZhmZWygIpUzvTNnFM
9Yyal7B6lkuHcFkK1wUiQYxkjYqfGPgvFu+4hns8wFOIBtzS1wMKs9A0H9Sm
KZhmVmSXCekmJgZRbyLoa2PHg5QL6wRmxGVy47K4uzq9iojPeKZ1VhMw34Lb
xmgVM51tdI2K2OfPJAP9nyMk05SWUG+bapWlYlenxTjdCwUIjfuB7rd9T3AQ
M5PPuBwbAvqGvTEzq7OW67WHp2K3pYC4ukcrX+E+xwagcipwtWaPNby1d09L
G8dpoAylmmmirSy/3W1goGVoOgwzX3I9LjlJOyw0bIKIkO/5vtC3e4+9saFJ
qDYIr566jCAUFYi0pw+7exTZgKX72w+3ruSAeUvq1rZhDVT+vfmJeAuIQarZ
SVRa+ghunGa9NWMywYrPYP2tTo7wn6Ovf+6K/jwSr6Z6ZgrrR9V/22kDkARK
QcJ2vm7bLoIfptcoGk997+k4w2KBsl6O6Pd3U16AR7Vzbs2hwO2OeN6nWDFc
g4/OfKSs3w/qRKVEXTD8MPxHTpmReKSHmx6NPMR3CZgVinlv4JU064vd1ICI
iKWEiff341Px+Obg8QfxF0AUTP1sJN4he8BbB6m2iYFgrpYdRri/Zh7VO/Qq
zNXUP4Oy3rYpldCxNKpevM2tpnIMo0sQI98weiLgK2RO7uuw71R+YFhfty4x
gPn46UXBmi13a2iTNQWIDHmQ+H1qNxU/HVrfEvus/uTt1Q0qTkHQB7LDLnYa
rXYn1KjQQvu8P4r+KHYY2jujv/1rG4UPhI6//XsdRDK53UeYz6i1zHJDjXP6
QpD7CfmZwRbHMf/+l5H4XJsgduqTITvXA1wcxuXv8XQ+WKCzJLA7TtUBLtPt
ycRkys13vu434r4+nZvDOjlvJbXC0A6e8/dN8PcueXevyd5tge0m8SbWYHeC
foAKiavlS7H+A1otk0wblw/hY7cO8KRfVkA1yoU1+0+Alk4OAseYodnmojmZ
g6gGQr7Cpt1KTSLBT56SGWLuA873m+3HL3inzsXx9Am5lO5Wub5EG6rT1JS1
qcHENcD2umIL2rPMKl7J6d8ygBOMOPAf91k+iHerYs2gtudeyBxkh4fq3cPf
3gz3Qt9MvJBmbJ+EEaDOaOTZgh+t+1LPx/bJkgYbMYE5nt376c01g7qwXKDL
lxbb+kKToP/K51jiizglpsib+VKf1aR/oetqyuMXdH6JvowGvZ9R50L/c7sG
T4EUToLjyBGHR3sQfJ8TNcTOeBSBIa1e0XuCZwoihSgXtJ9QyWgZRBf1q5X2
tQg0DLdouCr8rICP1+PLg/sP7eEDv3rDLq3K0DZ8VOqIxGuqyHms5zXpebvC
DBl6fE/FjW8LGDBoLmRW0xmud4veW6H978ATtPtykYGHkR64rUaXf/vZIZCL
9mntQdBx8qVHQfdKtZiQzzaC3ot0ew3yRH12qMbp9VuQQ2BGULzZfd2b9mfl
LpGs+OiXDGknVzmND1QH959pth3WjSqWMH8NB1/h4EC9DPHvgrXfJZeOGsf0
80XcYSstAmhTgdNqD1KEVWbjFBzvOXDyKpF7vyOY5KemaD+V8+QzKpubbvfW
RdG7xlemaGZ1mqEhloBdz03heVaxebr7rBFcJXuEZKbo/EH04e1n+M0ttM3E
Z9SbPTqRCO9E4yD6us91ZF/GWWf7TW19gud0S6DnqtuKx4hPXOtCwIMJNuXq
acHOJVUpfzITb8jqVIfR8xn/zXlOjug3Rz7xpLMDTgQaumuGB/eRr2x358Qu
UhrC/c6PuE/TiV84bFK/FX6vspxV/rASzYmjUB+/MDS4lYAq7oeM9F3x09nN
zaeL8e3t+PLnT9fHN8cXZ3dnN94xQ1a16WhNHN3B8qIwJTT3JB6xxPHlh+Pz
8em6xNfxmiuouFo/cay+28X7awHc88rerJnPse0NN3QatbVete5Bu/l0fH/3
vt6VUGVJXZuU/Omp+cIr4W4eBrC1hCLeExKnkzENAdsI0LoFgTuHJ8Q24g1s
cHMJL0N6Rj6h5fLq0/j0+tYL/yEW54YPkumFRleoPwRBIVKZnjUHvZBWagXm
xidqnrmFsyymQH6MbF+7HvXkb91Bo6wmrEy41jfjl/FBZn+eRPbQIekqbvQC
1Cf+5QQN1EWRQcK6Um7JhSmqjFU29Shjg9P+bFMLfk3n6HUpbo/Hn1Hh3yTp
abfT16eZ4eSpd4xEaS3LB//aCuyz/NABc0PA/N9N9e7VvIb+aqWdNcan540R
PYz6THmxiCzMY3hP0rGxbRXb9936zKfoC8v5NH5RuNVLkA35eI6Bwnfiqyn3
4YlHRdudtyibGkDXi/pxvVDVVWH9FObJslRzGY+c7V3Md58uKRl1+ch+fajv
uIFPW1zHncfXCQr9zeE/SUbC4TEdyz7SAZk/62HqkRM+5To2ltxj886RRP0K
D82u6fi9PrfwkyNUHLUm7z/b8TgDdtv9DfDoXmdfTi9UwwfWecaLQeqxjZdi
tDEFjbZyYh+Fmlq81Pm3SekobKD3fwF3zTR966SraB5OlQ2zcfcY2Zr+gTqd
ltv2kbpg2/BOXqapSqNwSOU4MylPH9Gg+UvnUTpO+sKvHcC7w+xzyu/wi95M
MOr96k4Bh7+dYazZrCI0DfCbPeo3aKutegpOJ0l8o1kaOFxaQ39tgnHCNY/i
Kr3Req4xt3W8c3xN7wmHXUFb/tyjbXZyS+soDOrbSsy40ZU+7Uw93E4q13md
DRvT/A+unhg2yH/Mk4q4VZjlqaOe0Nvd9s+6o38AmrebHysuAAA=

-->

</rfc>

